{
  "siteTitle": "Caleb’s College Progress",
  "siteSubtitle": "Tracking my academic journey at The University of Toledo.",
  "about": "I am beginning at The University of Toledo through Exploratory Studies while preparing for a future transition into Cyber Security. This page shares my academic progress, semester milestones, registered coursework, and later in the semester, grade updates.",
  "semester": "Fall 2026",
  "semesterStart": "2026-08-31",
  "totalCreditHours": 14,
  "assignmentsCompleted": 0,
  "assignmentsTotal": 0,
  "overallProgress": 0,
  "courses": [
    {
      "name": "College Composition I",
      "term": "Fall 2026",
      "hours": 3,
      "description": "Developing writing and communication skills for college and technical work.",
      "status": "Registered",
      "gradeLetter": "",
      "gradeScore": "",
      "latestAssignment": "",
      "latestAssignmentScore": "",
      "progress": 0
    },
    {
      "name": "Introduction to Logic",
      "term": "Fall 2026",
      "hours": 3,
      "description": "Developing formal reasoning and analytical thinking for future Cyber Security study.",
      "status": "Registered",
      "gradeLetter": "",
      "gradeScore": "",
      "latestAssignment": "",
      "latestAssignmentScore": "",
      "progress": 0
    },
    {
      "name": "Managing Diversity in the Workplace",
      "term": "Fall 2026",
      "hours": 3,
      "description": "Building teamwork, professionalism, and workplace awareness.",
      "status": "Registered",
      "gradeLetter": "",
      "gradeScore": "",
      "latestAssignment": "",
      "latestAssignmentScore": "",
      "progress": 0
    },
    {
      "name": "Math Modeling Problem Solving",
      "term": "Fall 2026",
      "hours": 4,
      "description": "Building quantitative reasoning and structured problem-solving skills.",
      "status": "Registered",
      "gradeLetter": "",
      "gradeScore": "",
      "latestAssignment": "",
      "latestAssignmentScore": "",
      "progress": 0
    },
    {
      "name": "Orientation",
      "term": "Fall 2026",
      "hours": 1,
      "description": "Building a strong foundation for success in college.",
      "status": "Registered",
      "gradeLetter": "",
      "gradeScore": "",
      "latestAssignment": "",
      "latestAssignmentScore": "",
      "progress": 0
    }
  ],
  "updates": [
    "Finalized Fall 2026 course plan.",
    "Registered for 14 planned credit hours.",
    "Preparing for the first day of classes on August 31, 2026."
  ],
  "upcomingDates": [
    {
      "date": "Aug 31, 2026",
      "label": "First day of Fall 2026 classes"
    },
    {
      "date": "Sep 7, 2026",
      "label": "Labor Day — no classes"
    },
    {
      "date": "Oct 19–20, 2026",
      "label": "Fall Break"
    },
    {
      "date": "Nov 26–27, 2026",
      "label": "Thanksgiving Break"
    },
    {
      "date": "Dec 11, 2026",
      "label": "Last day of classes"
    },
    {
      "date": "Dec 14–18, 2026",
      "label": "Finals Week"
    }
  ],
  "goals": [
    "Begin Fall 2026 with a strong academic foundation.",
    "Build skills that support a future transition into Cyber Security.",
    "Track course progress consistently throughout the semester."
  ]
}
